LICENSE
README.md
setup.py
scalablevq/__init__.py
scalablevq/assign.py
scalablevq/build.py
scalablevq/decode.py
scalablevq/encode.py
scalablevq/known.py
scalablevq/merge.py
scalablevq/nbits.py
scalablevq/split.py
scalablevq/utils.py
scalablevq/visualize.py
scalablevq.egg-info/PKG-INFO
scalablevq.egg-info/SOURCES.txt
scalablevq.egg-info/dependency_links.txt
scalablevq.egg-info/requires.txt
scalablevq.egg-info/top_level.txt