Metadata-Version: 2.1
Name: scalablevq
Version: 1.7.1
Summary: Scalable Vector Quantization
Home-page: https://github.com/yindaheng98/ScalableVQ
Author: yindaheng98
Author-email: yindaheng98@gmail.com
Classifier: Programming Language :: Python :: 3
Classifier: License :: OSI Approved :: MIT License
Classifier: Operating System :: OS Independent
License-File: LICENSE
